dockerfile_compose/__init__.py
dockerfile_compose/__version__.py
dockerfile_compose/cli.py
dockerfile_compose/dockerfile_compose.py
dockerfile_compose-0.0.3.dist-info/METADATA
dockerfile_compose-0.0.3.dist-info/RECORD
dockerfile_compose-0.0.3.dist-info/WHEEL
dockerfile_compose-0.0.3.dist-info/entry_points.txt
dockerfile_compose-0.0.3.dist-info/top_level.txt
