Metadata-Version: 2.1
Name: dockerfile-compose
Version: 0.0.3
Summary: Utils for making dockerfiles from other dockerfiles
Home-page: https://github.com/austinpray/dockerfile-compose
Author: Austin Pray
Author-email: austin@austinpray.com
License: MIT
Platform: UNKNOWN
Classifier: License :: OSI Approved :: MIT License
Classifier: Programming Language :: Python
Classifier: Programming Language :: Python :: 3
Classifier: Programming Language :: Python :: 3.6
Classifier: Programming Language :: Python :: Implementation :: CPython
Classifier: Programming Language :: Python :: Implementation :: PyPy
Requires-Python: >=3.6.0
